pythion/__init__.py
pythion/src/__init__.py
pythion/src/commit_writer.py
pythion/src/doc_writer.py
pythion/src/file_handler.py
pythion/src/increase_version.py
pythion/src/indexer.py
pythion/src/make_tests.py
pythion/src/models/__init__.py
pythion/src/models/core_models.py
pythion/src/models/doc_writer_models.py
pythion/src/models/location_models.py
pythion/src/models/prompt_models.py
pythion/src/models/test_maker_models.py
pythion/tests/__init__.py
pythion/tests/src/__init__.py
pythion/tests/src/test_make_tests.py
pythion-1.0.26.dist-info/licenses/LICENSE
pythion-1.0.26.dist-info/METADATA
pythion-1.0.26.dist-info/WHEEL
pythion-1.0.26.dist-info/entry_points.txt
pythion-1.0.26.dist-info/top_level.txt
pythion-1.0.26.dist-info/RECORD
