Metadata-Version: 2.4
Name: pythion
Version: 1.0.26
Summary: AI-powered CLI tool for generating Python documentation strings effortlessly
Author-email: Asaniczka <asaniczka@gmail.com>
Maintainer-email: Asaniczka <asaniczka@gmail.com>
License: Apache-2.0
Project-URL: Homepage, https://github.com/asaniczka/pythion
Classifier: Development Status :: 4 - Beta
Classifier: Intended Audience :: Developers
Classifier: License :: OSI Approved :: Apache Software License
Classifier: Natural Language :: English
Classifier: Programming Language :: Python :: 3.10
Requires-Python: >=3.10
License-File: LICENSE
Requires-Dist: annotated-types>=0.7.0
Requires-Dist: anyio>=4.6.0
Requires-Dist: certifi>=2024.8.30
Requires-Dist: click>=8.1.7
Requires-Dist: distro>=1.9.0
Requires-Dist: h11>=0.14.0
Requires-Dist: httpcore>=1.0.5
Requires-Dist: httpx>=0.27.2
Requires-Dist: idna>=3.10
Requires-Dist: jiter>=0.5.0
Requires-Dist: markdown-it-py>=3.0.0
Requires-Dist: mdurl>=0.1.2
Requires-Dist: openai>=1.47.0
Requires-Dist: pydantic>=2.9.2
Requires-Dist: pydantic_core>=2.23.4
Requires-Dist: Pygments>=2.18.0
Requires-Dist: python-dotenv>=1.0.1
Requires-Dist: pyperclip>=1.9.0
Requires-Dist: rich>=13.8.1
Requires-Dist: sniffio>=1.3.1
Requires-Dist: tqdm>=4.66.5
Requires-Dist: typing_extensions>=4.12.2
Requires-Dist: wrapworks>=1.0.6
Dynamic: license-file
